kedlang/__init__.py
kedlang/ast.py
kedlang/builtins.py
kedlang/callstack.py
kedlang/cli.py
kedlang/cwdstack.py
kedlang/exceptions.py
kedlang/interpreter.py
kedlang/lexer.py
kedlang/parser.py
kedlang/symbol.py
kedlang/types.py
kedlang/visitor.py
kedlang-0.1.0.dist-info/AUTHORS.rst
kedlang-0.1.0.dist-info/LICENSE.txt
kedlang-0.1.0.dist-info/METADATA
kedlang-0.1.0.dist-info/WHEEL
kedlang-0.1.0.dist-info/entry_points.txt
kedlang-0.1.0.dist-info/top_level.txt
kedlang-0.1.0.dist-info/RECORD
