Metadata-Version: 2.1
Name: kedlang
Version: 0.1.0
Summary: Ked interpreter written in Python
Home-page: https://github.com/pyscaffold/pyscaffold/
Author: "Eoin O'Brien"
Author-email: eoin@tracworx.ai
License: gpl3
Project-URL: Documentation, https://pyscaffold.org/
Platform: any
Classifier: Development Status :: 4 - Beta
Classifier: Programming Language :: Python
License-File: LICENSE.txt
License-File: AUTHORS.rst
Requires-Dist: sly
Provides-Extra: testing
Requires-Dist: pytest ; extra == 'testing'
Requires-Dist: pytest-cov ; extra == 'testing'
